cli_tool_gptree/__init__.py
cli_tool_gptree/main.py
gptree_cli-1.5.0.dist-info/METADATA
gptree_cli-1.5.0.dist-info/WHEEL
gptree_cli-1.5.0.dist-info/entry_points.txt
gptree_cli-1.5.0.dist-info/top_level.txt
gptree_cli-1.5.0.dist-info/RECORD
