Metadata-Version: 2.1
Name: gptree-cli
Version: 1.5.0
Summary: A CLI tool to provide LLM context for coding projects by combining project files into a single text file (or clipboard text) with directory tree structure
Home-page: https://github.com/travisvn/gptree
Author: Travis Van Nimwegen
Author-email: cli@travisvn.com
License: GPLv3
Classifier: Programming Language :: Python :: 3
Classifier: License :: OSI Approved :: GNU General Public License v3 (GPLv3)
Classifier: Operating System :: OS Independent
Requires-Python: >=3.7
Requires-Dist: pathspec
Requires-Dist: pyperclip
